onelive_vgst/__init__.py
onelive_vgst/api_client.py
onelive_vgst/api_response.py
onelive_vgst/configuration.py
onelive_vgst/exceptions.py
onelive_vgst/py.typed
onelive_vgst/rest.py
onelive_vgst/api/__init__.py
onelive_vgst/api/customers_api.py
onelive_vgst/api/health_api.py
onelive_vgst/api/provider_matches_api.py
onelive_vgst/api/providers_api.py
onelive_vgst/api/sports_api.py
onelive_vgst/models/__init__.py
onelive_vgst/models/auth_entity_read.py
onelive_vgst/models/customer_create.py
onelive_vgst/models/customer_password_update.py
onelive_vgst/models/customer_read.py
onelive_vgst/models/customer_state_enum.py
onelive_vgst/models/customer_update.py
onelive_vgst/models/health_status.py
onelive_vgst/models/http_validation_error.py
onelive_vgst/models/location_inner.py
onelive_vgst/models/provider_create.py
onelive_vgst/models/provider_match_bulk_item.py
onelive_vgst/models/provider_match_read.py
onelive_vgst/models/provider_read.py
onelive_vgst/models/provider_update.py
onelive_vgst/models/sport_create.py
onelive_vgst/models/sport_read.py
onelive_vgst/models/sport_update.py
onelive_vgst/models/validation_error.py
onelive_vgst-0.1.1.dist-info/METADATA
onelive_vgst-0.1.1.dist-info/WHEEL
onelive_vgst-0.1.1.dist-info/top_level.txt
onelive_vgst-0.1.1.dist-info/RECORD
