Metadata-Version: 2.4
Name: onelive_vgst
Version: 0.1.1
Summary: OneLive VGST API
Home-page: 
Author: OpenAPI Generator community
Author-email: OpenAPI Generator Community <team@openapitools.org>
Project-URL: Repository, https://github.com/GIT_USER_ID/GIT_REPO_ID
Keywords: OpenAPI,OpenAPI-Generator,OneLive VGST API
Requires-Python: >=3.9
Requires-Dist: python-dateutil>=2.8.2
Requires-Dist: aiohttp>=3.8.4
Requires-Dist: aiohttp-retry>=2.8.3
Requires-Dist: pydantic>=2
Requires-Dist: typing-extensions>=4.7.1
Dynamic: author
